dubious/__init__.py
dubious/core/__init__.py
dubious/core/context.py
dubious/core/node.py
dubious/core/sample_session.py
dubious/core/sampleable.py
dubious/core/uncertain.py
dubious/distributions/__init__.py
dubious/distributions/beta.py
dubious/distributions/dist_helpers.py
dubious/distributions/lognormal.py
dubious/distributions/normal.py
dubious/distributions/uniform.py
dubious/umath/__init__.py
dubious/umath/umath.py
dubious/umath/ustats.py
dubious-0.3.0.dist-info/licenses/LICENSE
dubious-0.3.0.dist-info/METADATA
dubious-0.3.0.dist-info/WHEEL
dubious-0.3.0.dist-info/top_level.txt
dubious-0.3.0.dist-info/RECORD
