Metadata-Version: 2.4
Name: dubious
Version: 0.3.0
Summary: Dubious is a Python library for propagating uncertainty through numerical computations
Author-email: Flynn500 <flynnwilson101@gmail.com>
License: MIT License
Requires-Python: >=3.9
License-File: LICENSE
Requires-Dist: numpy>=1.23
Provides-Extra: test
Requires-Dist: pytest>=7; extra == "test"
Requires-Dist: scipy>=1.10; extra == "test"
Dynamic: license-file
